neosqlite/__init__.py
neosqlite/binary.py
neosqlite/bulk_operations.py
neosqlite/changestream.py
neosqlite/collection/__init__.py
neosqlite/collection/aggregation_cursor.py
neosqlite/collection/cursor.py
neosqlite/collection/datetime_query_processor.py
neosqlite/collection/datetime_utils.py
neosqlite/collection/index_manager.py
neosqlite/collection/json_helpers.py
neosqlite/collection/json_path_utils.py
neosqlite/collection/jsonb_support.py
neosqlite/collection/query_engine.py
neosqlite/collection/query_helper.py
neosqlite/collection/raw_batch_cursor.py
neosqlite/collection/sql_translator_unified.py
neosqlite/collection/temporary_table_aggregation.py
neosqlite/collection/text_search.py
neosqlite/collection/type_correction.py
neosqlite/connection.py
neosqlite/exceptions.py
neosqlite/gridfs/README.md
neosqlite/gridfs/__init__.py
neosqlite/gridfs/errors.py
neosqlite/gridfs/grid_file.py
neosqlite/gridfs/gridfs_bucket.py
neosqlite/gridfs/gridfs_legacy.py
neosqlite/objectid.py
neosqlite/query_operators.py
neosqlite/requests.py
neosqlite/results.py
neosqlite-1.2.2.dist-info/METADATA
neosqlite-1.2.2.dist-info/WHEEL
neosqlite-1.2.2.dist-info/licenses/LICENSE
neosqlite-1.2.2.dist-info/RECORD
