Metadata-Version: 2.4
Name: neosqlite
Version: 1.2.2
Summary: NoSQL for SQLite with PyMongo-like API
License: MIT
License-File: LICENSE
Keywords: nosql,sqlite,pymongo
Author: Chaiwat Suttipongsakul
Author-email: cwt@bashell.com
Requires-Python: >=3.10,<4.0
Classifier: Development Status :: 5 - Production/Stable
Classifier: License :: OSI Approved :: MIT License
Classifier: Operating System :: OS Independent
Classifier: Programming Language :: Python :: 3
Classifier: Programming Language :: Python :: 3.10
Classifier: Programming Language :: Python :: 3.11
Classifier: Programming Language :: Python :: 3.12
Classifier: Programming Language :: Python :: 3.13
Classifier: Programming Language :: Python :: 3.14
Classifier: Topic :: Software Development :: Libraries :: Python Modules
Provides-Extra: docs
Provides-Extra: jsonb
Provides-Extra: memory-constrained
Requires-Dist: furo (>=2025.7.19,<2026.0.0) ; extra == "docs"
Requires-Dist: pysqlite3-binary (>=0.5.4,<0.6.0) ; extra == "jsonb"
Requires-Dist: quez (>=1.1.1,<2.0.0) ; extra == "memory-constrained"
Requires-Dist: sphinx (>=8.1.0,<8.2.0) ; extra == "docs"
Project-URL: Documentation, https://neosqlite.readthedocs.io/en/latest/
Project-URL: Homepage, https://github.com/cwt/neosqlite
Project-URL: Repository, https://github.com/cwt/neosqlite
Project-URL: SourceHut Mirror, https://sr.ht/~cwt/neosqlite
